[{"action":"fill","selector":"#signup_free-element-11","valueKey":"campEmail"},{"action":"fill","selector":"#signup_free-element-12","valueKey":"campEmail"},{"action":"fill","selector":"#signup_free-element-13","valueKey":"passDirectory"},{"action":"fill","selector":"#signup_free-element-14","valueKey":"passDirectory"},
  {
    "action": "click",
    "selector": ".btn.btn-block.btn-warning.bold",
    "valueKey": "NextButtonSave"
  },

  {
    "action": "fill",
    "selector": "[name=\"listing_type\"]",
    "value": "Company"
  },
  {
    "action": "fill",
    "selector": "[name=\"profession_id\"]",
    "value": "profession_id"
  },
  {
    "action": "fill",
    "selector": "[name=\"first_name\"]",
    "valueKey": "contactFirstNameBox"
  },
  {
    "action": "fill",
    "selector": "[name=\"last_name\"]",
    "valueKey": "contactLastNameBox"
  },
  {
    "action": "fill",
    "selector": "[name=\"email\"]",
    "valueKey": "campEmail"
  },
  {
    "action": "fill",
    "selector": "[name=\"phone_number\"]",
    "valueKey": "contactTelephoneBox"
  },
  {
    "action": "fill",
    "selector": "[name=\"company\"]",
    "valueKey": "businessNameBox"
  },
  {
    "action": "fill",
    "selector": "[name=\"address1\"]",
    "valueKey": "line1"
  },
  {
    "action": "fill",
    "selector": "[name=\"address2\"]",
    "valueKey": "line2"
  },
  {
    "action": "fill",
    "selector": "[name=\"city\"]",
    "valueKey": "city"
  },
  {
    "action": "fill",
    "selector": "[name=\"state_ln\"]",
    "valueKey": "state"
  },
  {
    "action": "fill",
    "selector": "[name=\"country_ln\"]",
    "valueKey": "country"
  },
  {
    "action": "fill",
    "selector": "[name=\"country_code\"]",
    "valueKey": "countryabbv"
  },
  {
    "action": "fill",
    "selector": "[name=\"zip_code\"]",
    "valueKey": "zipcode"
  },
  {
    "action": "fill",
    "selector": "[name=\"website\"]",
    "valueKey": "websiteBox"
  },
  {
    "action": "fill",
    "selector": "[name=\"facebook\"]",
    "valueKey": "facebookBox"
  },
  {
    "action": "fill",
    "selector": "[name=\"twitter\"]",
    "valueKey": "twitterBox"
  },
  {
    "action": "fill",
    "selector": "[name=\"linkedin\"]",
    "valueKey": "linkedinBox"
  },
  {
    "action": "fill",
    "selector": "[name=\"youtube\"]",
    "valueKey": "youtubeBox"
  },
  {
    "action": "fill",
    "selector": "[name=\"instagram\"]",
    "valueKey": "instagramBox"
  },
  {
    "action": "fill",
    "selector": "[name=\"pinterest\"]",
    "valueKey": "pinterestBox"
  },
  {
    "action": "fill",
    "selector": "[name=\"tiktok\"]",
    "valueKey": "tiktokBox"
  },
  {
    "action": "click",
    "selector": "#member_contact_details_110-element-46",
    "valueKey": "NextButtonSave"
  },
  {
    "action": "click",
    "selector": ".btn.btn-lg.btn-primary.change-current-logo",
    "valueKey": "UploadButton"
  },
  {
    "action": "uploadImages",
    "selector": "#logo-img-upload-input",
    "valueKey": "logoBox"
  },
  {
    "action": "click",
    "selector": ".btn.btn-primary.bold.upload-logo.col-md-8",
    "valueKey": "UploadButtonSave"
  },
    {
    "action": "click",
    "selector": ".btn.btn-success.btn-lg.btn-block",
    "valueKey": "NextButtonSave"
  },
  {
    "action": "fill",
    "selector": "#member_listing_details_82-element-10",
    "valueKey": "yearFormationBox"
  },
  {
    "action": "fill",
    "selector": "#member_listing_details_82-element-12",
    "valueKey": "businessHoursBox"
  },
  {
    "action": "fill",
    "selector": "#member_listing_details_82-element-13",
    "valueKey": "paymentMethodsBox"
  },
  {
    "action": "click",
    "selector": ".btn.btn-lg.btn-success.col-sm-offset-2",
    "valueKey": "NextButtonSave"
  },
	{
	  "action": "richFill",
	  "selector": ".CodeMirror.cm-s-default.CodeMirror-wrap",
	  "valueKey": "longDescriptionBox"
	}

]
